MANIFEST.in
README.rst
setup.py
src/AUTHORS.txt
src/HISTORY.txt
src/README.txt
src/sphinxjp/__init__.py
src/sphinxjp.themes.tinkerturquoise.egg-info/PKG-INFO
src/sphinxjp.themes.tinkerturquoise.egg-info/SOURCES.txt
src/sphinxjp.themes.tinkerturquoise.egg-info/dependency_links.txt
src/sphinxjp.themes.tinkerturquoise.egg-info/entry_points.txt
src/sphinxjp.themes.tinkerturquoise.egg-info/namespace_packages.txt
src/sphinxjp.themes.tinkerturquoise.egg-info/not-zip-safe
src/sphinxjp.themes.tinkerturquoise.egg-info/requires.txt
src/sphinxjp.themes.tinkerturquoise.egg-info/top_level.txt
src/sphinxjp/themes/__init__.py
src/sphinxjp/themes/tinkerturquoise/__init__.py
src/sphinxjp/themes/tinkerturquoise/templates/tinkerturquoise/layout.html
src/sphinxjp/themes/tinkerturquoise/templates/tinkerturquoise/theme.conf
src/sphinxjp/themes/tinkerturquoise/templates/tinkerturquoise/static/pygments.css
src/sphinxjp/themes/tinkerturquoise/templates/tinkerturquoise/static/tinkerturquoise.css_t